README.rst
setup.cfg
setup.py
taxonomylite.py
taxonomylite.egg-info/PKG-INFO
taxonomylite.egg-info/SOURCES.txt
taxonomylite.egg-info/dependency_links.txt
taxonomylite.egg-info/top_level.txt