Metadata-Version: 1.1
Name: taxonomylite
Version: 1.0.4
Summary: Traverse NCBI Taxonomy data using SQLite
Home-page: https://github.com/mobiusklein/taxonomylite
Author: Joshua Klein, Sukru N. Kaymakcalan, Christian Wake
Author-email: ['joshua.adam.klein@gmail.com', 'skaymakca@gmail.com', 'cwake@bu.edu']
License: UNKNOWN
Platform: UNKNOWN
Classifier: Development Status :: 4 - Beta
Classifier: Intended Audience :: Science/Research
Classifier: License :: OSI Approved :: BSD License
Classifier: Topic :: Scientific/Engineering :: Bio-Informatics
